ttblackjack/__init__.py
ttblackjack/__main__.py
ttblackjack/algorithm.py
ttblackjack/card.py
ttblackjack/cli.py
ttblackjack/config.toml
ttblackjack/game.py
ttblackjack/hand.py
ttblackjack/player.py
ttblackjack/suit.py
ttblackjack-0.1.0a2.dist-info/entry_points.txt
ttblackjack-0.1.0a2.dist-info/LICENSE
ttblackjack-0.1.0a2.dist-info/WHEEL
ttblackjack-0.1.0a2.dist-info/METADATA
ttblackjack-0.1.0a2.dist-info/RECORD
